{
  "resourceType": "Bundle",
  "id": "51688ef1-4cba-4a5d-ba1c-ed3e28f26c38",
  "type": "collection",
  "entry": [
    {
      "resource": {
        "resourceType": "Patient",
        "id": "patient-6533",
        "gender": "male",
        "birthDate": "1958-01-23",
        "meta": {
          "lastUpdated": "2024-03-18"
        },
        "extension": [
          {
            "valueBoolean": false
          }
        ],
        "_recordStart": "2023-06-25"
      }
    },
    {
      "resource": {
        "resourceType": "Condition",
        "clinicalStatus": {
          "coding": [
            {
              "code": "resolved"
            }
          ]
        },
        "severity": {
          "text": "moderate"
        },
        "code": {
          "coding": [
            {
              "code": "J44.9",
              "display": "COPD"
            }
          ]
        }
      }
    },
    {
      "resource": {
        "resourceType": "Condition",
        "clinicalStatus": {
          "coding": [
            {
              "code": "resolved"
            }
          ]
        },
        "severity": {
          "text": "mild"
        },
        "code": {
          "coding": [
            {
              "code": "N18.9",
              "display": "Chronic Kidney Disease"
            }
          ]
        }
      }
    },
    {
      "resource": {
        "resourceType": "Condition",
        "clinicalStatus": {
          "coding": [
            {
              "code": "resolved"
            }
          ]
        },
        "severity": {
          "text": "mild"
        },
        "code": {
          "coding": [
            {
              "code": "M19.90",
              "display": "Osteoarthritis"
            }
          ]
        }
      }
    },
    {
      "resource": {
        "resourceType": "Condition",
        "clinicalStatus": {
          "coding": [
            {
              "code": "resolved"
            }
          ]
        },
        "severity": {
          "text": "mild"
        },
        "code": {
          "coding": [
            {
              "code": "I10",
              "display": "Hypertension"
            }
          ]
        }
      }
    },
    {
      "resource": {
        "resourceType": "Encounter",
        "id": "enc-patient-6533-0",
        "status": "finished",
        "period": {
          "start": "2024-01-01"
        }
      }
    },
    {
      "resource": {
        "resourceType": "Observation",
        "effectiveDateTime": "2024-01-01",
        "code": {
          "coding": [
            {
              "code": "2160-0",
              "display": "Creatinine"
            }
          ]
        },
        "valueQuantity": {
          "value": 1.9,
          "unit": "mg/dL"
        },
        "encounter": {
          "reference": "Encounter/enc-patient-6533-0"
        }
      }
    },
    {
      "resource": {
        "resourceType": "Observation",
        "effectiveDateTime": "2024-01-01",
        "code": {
          "coding": [
            {
              "code": "8480-6",
              "display": "Systolic Blood Pressure"
            }
          ]
        },
        "valueQuantity": {
          "value": 158.93,
          "unit": "mmHg"
        },
        "encounter": {
          "reference": "Encounter/enc-patient-6533-0"
        }
      }
    },
    {
      "resource": {
        "resourceType": "Encounter",
        "id": "enc-patient-6533-1",
        "status": "finished",
        "period": {
          "start": "2024-08-11"
        }
      }
    },
    {
      "resource": {
        "resourceType": "Observation",
        "effectiveDateTime": "2024-08-11",
        "code": {
          "coding": [
            {
              "code": "2160-0",
              "display": "Creatinine"
            }
          ]
        },
        "valueQuantity": {
          "value": 1.96,
          "unit": "mg/dL"
        },
        "encounter": {
          "reference": "Encounter/enc-patient-6533-1"
        }
      }
    },
    {
      "resource": {
        "resourceType": "Observation",
        "effectiveDateTime": "2024-08-11",
        "code": {
          "coding": [
            {
              "code": "8480-6",
              "display": "Systolic Blood Pressure"
            }
          ]
        },
        "valueQuantity": {
          "value": 149.26,
          "unit": "mmHg"
        },
        "encounter": {
          "reference": "Encounter/enc-patient-6533-1"
        }
      }
    },
    {
      "resource": {
        "resourceType": "Encounter",
        "id": "enc-patient-6533-2",
        "status": "finished",
        "period": {
          "start": "2024-10-18"
        }
      }
    },
    {
      "resource": {
        "resourceType": "Observation",
        "effectiveDateTime": "2024-10-18",
        "code": {
          "coding": [
            {
              "code": "2160-0",
              "display": "Creatinine"
            }
          ]
        },
        "valueQuantity": {
          "value": 5.0,
          "unit": "mg/dL"
        },
        "encounter": {
          "reference": "Encounter/enc-patient-6533-2"
        }
      }
    },
    {
      "resource": {
        "resourceType": "Observation",
        "effectiveDateTime": "2024-10-18",
        "code": {
          "coding": [
            {
              "code": "8480-6",
              "display": "Systolic Blood Pressure"
            }
          ]
        },
        "valueQuantity": {
          "value": 113.96,
          "unit": "mmHg"
        },
        "encounter": {
          "reference": "Encounter/enc-patient-6533-2"
        }
      }
    }
  ]
}