{
  "resourceType": "Bundle",
  "id": "dcb3ff11-a09a-47ad-b17e-252e31c97379",
  "type": "collection",
  "entry": [
    {
      "resource": {
        "resourceType": "Patient",
        "id": "patient-4952",
        "gender": "male",
        "birthDate": "1995-01-14",
        "meta": {
          "lastUpdated": "2026-11-20"
        },
        "extension": [
          {
            "valueBoolean": false
          }
        ],
        "_recordStart": "2024-04-23"
      }
    },
    {
      "resource": {
        "resourceType": "Condition",
        "clinicalStatus": {
          "coding": [
            {
              "code": "resolved"
            }
          ]
        },
        "severity": {
          "text": "mild"
        },
        "code": {
          "coding": [
            {
              "code": "E11.9",
              "display": "Type 2 Diabetes Mellitus"
            }
          ]
        }
      }
    },
    {
      "resource": {
        "resourceType": "Condition",
        "clinicalStatus": {
          "coding": [
            {
              "code": "resolved"
            }
          ]
        },
        "severity": {
          "text": "moderate"
        },
        "code": {
          "coding": [
            {
              "code": "E03.9",
              "display": "Hypothyroidism"
            }
          ]
        }
      }
    },
    {
      "resource": {
        "resourceType": "Encounter",
        "id": "enc-patient-4952-0",
        "status": "finished",
        "period": {
          "start": "2024-05-14"
        }
      }
    },
    {
      "resource": {
        "resourceType": "Observation",
        "effectiveDateTime": "2024-05-14",
        "code": {
          "coding": [
            {
              "code": "4548-4",
              "display": "Hemoglobin A1c"
            }
          ]
        },
        "valueQuantity": {
          "value": 9.53,
          "unit": "%"
        },
        "encounter": {
          "reference": "Encounter/enc-patient-4952-0"
        }
      }
    },
    {
      "resource": {
        "resourceType": "Encounter",
        "id": "enc-patient-4952-1",
        "status": "finished",
        "period": {
          "start": "2024-05-25"
        }
      }
    },
    {
      "resource": {
        "resourceType": "Observation",
        "effectiveDateTime": "2024-05-25",
        "code": {
          "coding": [
            {
              "code": "4548-4",
              "display": "Hemoglobin A1c"
            }
          ]
        },
        "valueQuantity": {
          "value": 10.22,
          "unit": "%"
        },
        "encounter": {
          "reference": "Encounter/enc-patient-4952-1"
        }
      }
    },
    {
      "resource": {
        "resourceType": "Encounter",
        "id": "enc-patient-4952-2",
        "status": "finished",
        "period": {
          "start": "2024-06-06"
        }
      }
    },
    {
      "resource": {
        "resourceType": "Encounter",
        "id": "enc-patient-4952-3",
        "status": "finished",
        "period": {
          "start": "2024-09-27"
        }
      }
    },
    {
      "resource": {
        "resourceType": "Observation",
        "effectiveDateTime": "2024-09-27",
        "code": {
          "coding": [
            {
              "code": "4548-4",
              "display": "Hemoglobin A1c"
            }
          ]
        },
        "valueQuantity": {
          "value": 8.51,
          "unit": "%"
        },
        "encounter": {
          "reference": "Encounter/enc-patient-4952-3"
        }
      }
    },
    {
      "resource": {
        "resourceType": "Encounter",
        "id": "enc-patient-4952-4",
        "status": "finished",
        "period": {
          "start": "2025-02-15"
        }
      }
    },
    {
      "resource": {
        "resourceType": "Observation",
        "effectiveDateTime": "2025-02-15",
        "code": {
          "coding": [
            {
              "code": "4548-4",
              "display": "Hemoglobin A1c"
            }
          ]
        },
        "valueQuantity": {
          "value": 10.68,
          "unit": "%"
        },
        "encounter": {
          "reference": "Encounter/enc-patient-4952-4"
        }
      }
    },
    {
      "resource": {
        "resourceType": "Encounter",
        "id": "enc-patient-4952-5",
        "status": "finished",
        "period": {
          "start": "2025-03-23"
        }
      }
    },
    {
      "resource": {
        "resourceType": "Observation",
        "effectiveDateTime": "2025-03-23",
        "code": {
          "coding": [
            {
              "code": "4548-4",
              "display": "Hemoglobin A1c"
            }
          ]
        },
        "valueQuantity": {
          "value": 7.15,
          "unit": "%"
        },
        "encounter": {
          "reference": "Encounter/enc-patient-4952-5"
        }
      }
    },
    {
      "resource": {
        "resourceType": "Encounter",
        "id": "enc-patient-4952-6",
        "status": "finished",
        "period": {
          "start": "2025-06-04"
        }
      }
    },
    {
      "resource": {
        "resourceType": "Observation",
        "effectiveDateTime": "2025-06-04",
        "code": {
          "coding": [
            {
              "code": "4548-4",
              "display": "Hemoglobin A1c"
            }
          ]
        },
        "valueQuantity": {
          "value": 7.62,
          "unit": "%"
        },
        "encounter": {
          "reference": "Encounter/enc-patient-4952-6"
        }
      }
    },
    {
      "resource": {
        "resourceType": "Encounter",
        "id": "enc-patient-4952-7",
        "status": "finished",
        "period": {
          "start": "2026-06-27"
        }
      }
    },
    {
      "resource": {
        "resourceType": "Observation",
        "effectiveDateTime": "2026-06-27",
        "code": {
          "coding": [
            {
              "code": "4548-4",
              "display": "Hemoglobin A1c"
            }
          ]
        },
        "valueQuantity": {
          "value": 7.45,
          "unit": "%"
        },
        "encounter": {
          "reference": "Encounter/enc-patient-4952-7"
        }
      }
    }
  ]
}