{
  "resourceType": "Bundle",
  "id": "916f9a81-e23a-4565-8cb1-757664124f66",
  "type": "collection",
  "entry": [
    {
      "resource": {
        "resourceType": "Patient",
        "id": "patient-1852",
        "gender": "female",
        "birthDate": "1961-01-22",
        "meta": {
          "lastUpdated": "2023-04-06"
        },
        "extension": [
          {
            "valueBoolean": false
          }
        ],
        "_recordStart": "2022-05-03"
      }
    },
    {
      "resource": {
        "resourceType": "Condition",
        "clinicalStatus": {
          "coding": [
            {
              "code": "resolved"
            }
          ]
        },
        "severity": {
          "text": "severe"
        },
        "code": {
          "coding": [
            {
              "code": "J45.909",
              "display": "Asthma"
            }
          ]
        }
      }
    },
    {
      "resource": {
        "resourceType": "Condition",
        "clinicalStatus": {
          "coding": [
            {
              "code": "resolved"
            }
          ]
        },
        "severity": {
          "text": "moderate"
        },
        "code": {
          "coding": [
            {
              "code": "I10",
              "display": "Hypertension"
            }
          ]
        }
      }
    },
    {
      "resource": {
        "resourceType": "Condition",
        "clinicalStatus": {
          "coding": [
            {
              "code": "resolved"
            }
          ]
        },
        "severity": {
          "text": "moderate"
        },
        "code": {
          "coding": [
            {
              "code": "F32.9",
              "display": "Depression"
            }
          ]
        }
      }
    },
    {
      "resource": {
        "resourceType": "Condition",
        "clinicalStatus": {
          "coding": [
            {
              "code": "resolved"
            }
          ]
        },
        "severity": {
          "text": "severe"
        },
        "code": {
          "coding": [
            {
              "code": "E03.9",
              "display": "Hypothyroidism"
            }
          ]
        }
      }
    },
    {
      "resource": {
        "resourceType": "Encounter",
        "id": "enc-patient-1852-0",
        "status": "finished",
        "period": {
          "start": "2022-10-07"
        }
      }
    },
    {
      "resource": {
        "resourceType": "Encounter",
        "id": "enc-patient-1852-1",
        "status": "finished",
        "period": {
          "start": "2022-11-20"
        }
      }
    },
    {
      "resource": {
        "resourceType": "Observation",
        "effectiveDateTime": "2022-11-20",
        "code": {
          "coding": [
            {
              "code": "8480-6",
              "display": "Systolic Blood Pressure"
            }
          ]
        },
        "valueQuantity": {
          "value": 145.34,
          "unit": "mmHg"
        },
        "encounter": {
          "reference": "Encounter/enc-patient-1852-1"
        }
      }
    },
    {
      "resource": {
        "resourceType": "Encounter",
        "id": "enc-patient-1852-2",
        "status": "finished",
        "period": {
          "start": "2023-04-02"
        }
      }
    },
    {
      "resource": {
        "resourceType": "Observation",
        "effectiveDateTime": "2023-04-02",
        "code": {
          "coding": [
            {
              "code": "8480-6",
              "display": "Systolic Blood Pressure"
            }
          ]
        },
        "valueQuantity": {
          "value": 154.12,
          "unit": "mmHg"
        },
        "encounter": {
          "reference": "Encounter/enc-patient-1852-2"
        }
      }
    },
    {
      "resource": {
        "resourceType": "Encounter",
        "id": "enc-patient-1852-3",
        "status": "finished",
        "period": {
          "start": "2023-12-07"
        }
      }
    },
    {
      "resource": {
        "resourceType": "Observation",
        "effectiveDateTime": "2023-12-07",
        "code": {
          "coding": [
            {
              "code": "8480-6",
              "display": "Systolic Blood Pressure"
            }
          ]
        },
        "valueQuantity": {
          "value": 118.05,
          "unit": "mmHg"
        },
        "encounter": {
          "reference": "Encounter/enc-patient-1852-3"
        }
      }
    },
    {
      "resource": {
        "resourceType": "Encounter",
        "id": "enc-patient-1852-4",
        "status": "finished",
        "period": {
          "start": "2024-04-05"
        }
      }
    },
    {
      "resource": {
        "resourceType": "Observation",
        "effectiveDateTime": "2024-04-05",
        "code": {
          "coding": [
            {
              "code": "8480-6",
              "display": "Systolic Blood Pressure"
            }
          ]
        },
        "valueQuantity": {
          "value": 123.89,
          "unit": "mmHg"
        },
        "encounter": {
          "reference": "Encounter/enc-patient-1852-4"
        }
      }
    },
    {
      "resource": {
        "resourceType": "Encounter",
        "id": "enc-patient-1852-5",
        "status": "finished",
        "period": {
          "start": "2024-04-05"
        }
      }
    },
    {
      "resource": {
        "resourceType": "Observation",
        "effectiveDateTime": "2024-04-05",
        "code": {
          "coding": [
            {
              "code": "8480-6",
              "display": "Systolic Blood Pressure"
            }
          ]
        },
        "valueQuantity": {
          "value": 147.77,
          "unit": "mmHg"
        },
        "encounter": {
          "reference": "Encounter/enc-patient-1852-5"
        }
      }
    },
    {
      "resource": {
        "resourceType": "Encounter",
        "id": "enc-patient-1852-6",
        "status": "finished",
        "period": {
          "start": "2024-05-27"
        }
      }
    },
    {
      "resource": {
        "resourceType": "Observation",
        "effectiveDateTime": "2024-05-27",
        "code": {
          "coding": [
            {
              "code": "8480-6",
              "display": "Systolic Blood Pressure"
            }
          ]
        },
        "valueQuantity": {
          "value": 174.06,
          "unit": "mmHg"
        },
        "encounter": {
          "reference": "Encounter/enc-patient-1852-6"
        }
      }
    },
    {
      "resource": {
        "resourceType": "Encounter",
        "id": "enc-patient-1852-7",
        "status": "finished",
        "period": {
          "start": "2024-07-01"
        }
      }
    }
  ]
}