{
  "resourceType": "Bundle",
  "id": "cef9508b-108e-4b35-ba77-8a4cb7e5bf4d",
  "type": "collection",
  "entry": [
    {
      "resource": {
        "resourceType": "Patient",
        "id": "patient-8504",
        "gender": "male",
        "birthDate": "1948-01-26",
        "meta": {
          "lastUpdated": "2026-01-06"
        },
        "extension": [
          {
            "valueBoolean": true
          }
        ],
        "_recordStart": "2020-08-10"
      }
    },
    {
      "resource": {
        "resourceType": "Condition",
        "clinicalStatus": {
          "coding": [
            {
              "code": "active"
            }
          ]
        },
        "severity": {
          "text": "moderate"
        },
        "code": {
          "coding": [
            {
              "code": "J44.9",
              "display": "COPD"
            }
          ]
        }
      }
    },
    {
      "resource": {
        "resourceType": "Condition",
        "clinicalStatus": {
          "coding": [
            {
              "code": "active"
            }
          ]
        },
        "severity": {
          "text": "moderate"
        },
        "code": {
          "coding": [
            {
              "code": "F32.9",
              "display": "Depression"
            }
          ]
        }
      }
    },
    {
      "resource": {
        "resourceType": "Condition",
        "clinicalStatus": {
          "coding": [
            {
              "code": "active"
            }
          ]
        },
        "severity": {
          "text": "moderate"
        },
        "code": {
          "coding": [
            {
              "code": "I25.10",
              "display": "Coronary Artery Disease"
            }
          ]
        }
      }
    },
    {
      "resource": {
        "resourceType": "Encounter",
        "id": "enc-patient-8504-0",
        "status": "finished",
        "period": {
          "start": "2021-06-27"
        }
      }
    },
    {
      "resource": {
        "resourceType": "Encounter",
        "id": "enc-patient-8504-1",
        "status": "finished",
        "period": {
          "start": "2021-07-15"
        }
      }
    },
    {
      "resource": {
        "resourceType": "Encounter",
        "id": "enc-patient-8504-2",
        "status": "finished",
        "period": {
          "start": "2021-09-16"
        }
      }
    },
    {
      "resource": {
        "resourceType": "Encounter",
        "id": "enc-patient-8504-3",
        "status": "finished",
        "period": {
          "start": "2022-03-09"
        }
      }
    },
    {
      "resource": {
        "resourceType": "Encounter",
        "id": "enc-patient-8504-4",
        "status": "finished",
        "period": {
          "start": "2022-05-21"
        }
      }
    }
  ]
}