{
  "resourceType": "Bundle",
  "id": "952cc775-f3d1-4caa-8b1e-150343c50720",
  "type": "collection",
  "entry": [
    {
      "resource": {
        "resourceType": "Patient",
        "id": "patient-6951",
        "gender": "female",
        "birthDate": "1975-01-19",
        "meta": {
          "lastUpdated": "2022-05-03"
        },
        "extension": [
          {
            "valueBoolean": false
          }
        ],
        "_recordStart": "2020-11-30"
      }
    },
    {
      "resource": {
        "resourceType": "Condition",
        "clinicalStatus": {
          "coding": [
            {
              "code": "resolved"
            }
          ]
        },
        "severity": {
          "text": "mild"
        },
        "code": {
          "coding": [
            {
              "code": "N18.9",
              "display": "Chronic Kidney Disease"
            }
          ]
        }
      }
    },
    {
      "resource": {
        "resourceType": "Condition",
        "clinicalStatus": {
          "coding": [
            {
              "code": "resolved"
            }
          ]
        },
        "severity": {
          "text": "severe"
        },
        "code": {
          "coding": [
            {
              "code": "E03.9",
              "display": "Hypothyroidism"
            }
          ]
        }
      }
    },
    {
      "resource": {
        "resourceType": "Condition",
        "clinicalStatus": {
          "coding": [
            {
              "code": "resolved"
            }
          ]
        },
        "severity": {
          "text": "moderate"
        },
        "code": {
          "coding": [
            {
              "code": "J45.909",
              "display": "Asthma"
            }
          ]
        }
      }
    },
    {
      "resource": {
        "resourceType": "Encounter",
        "id": "enc-patient-6951-0",
        "status": "finished",
        "period": {
          "start": "2021-04-04"
        }
      }
    },
    {
      "resource": {
        "resourceType": "Observation",
        "effectiveDateTime": "2021-04-04",
        "code": {
          "coding": [
            {
              "code": "2160-0",
              "display": "Creatinine"
            }
          ]
        },
        "valueQuantity": {
          "value": 5.0,
          "unit": "mg/dL"
        },
        "encounter": {
          "reference": "Encounter/enc-patient-6951-0"
        }
      }
    },
    {
      "resource": {
        "resourceType": "Encounter",
        "id": "enc-patient-6951-1",
        "status": "finished",
        "period": {
          "start": "2022-01-14"
        }
      }
    },
    {
      "resource": {
        "resourceType": "Observation",
        "effectiveDateTime": "2022-01-14",
        "code": {
          "coding": [
            {
              "code": "2160-0",
              "display": "Creatinine"
            }
          ]
        },
        "valueQuantity": {
          "value": 2.29,
          "unit": "mg/dL"
        },
        "encounter": {
          "reference": "Encounter/enc-patient-6951-1"
        }
      }
    },
    {
      "resource": {
        "resourceType": "Encounter",
        "id": "enc-patient-6951-2",
        "status": "finished",
        "period": {
          "start": "2022-01-24"
        }
      }
    },
    {
      "resource": {
        "resourceType": "Observation",
        "effectiveDateTime": "2022-01-24",
        "code": {
          "coding": [
            {
              "code": "2160-0",
              "display": "Creatinine"
            }
          ]
        },
        "valueQuantity": {
          "value": 2.42,
          "unit": "mg/dL"
        },
        "encounter": {
          "reference": "Encounter/enc-patient-6951-2"
        }
      }
    },
    {
      "resource": {
        "resourceType": "Encounter",
        "id": "enc-patient-6951-3",
        "status": "finished",
        "period": {
          "start": "2022-05-12"
        }
      }
    },
    {
      "resource": {
        "resourceType": "Observation",
        "effectiveDateTime": "2022-05-12",
        "code": {
          "coding": [
            {
              "code": "2160-0",
              "display": "Creatinine"
            }
          ]
        },
        "valueQuantity": {
          "value": 3.68,
          "unit": "mg/dL"
        },
        "encounter": {
          "reference": "Encounter/enc-patient-6951-3"
        }
      }
    },
    {
      "resource": {
        "resourceType": "Encounter",
        "id": "enc-patient-6951-4",
        "status": "finished",
        "period": {
          "start": "2022-07-05"
        }
      }
    },
    {
      "resource": {
        "resourceType": "Observation",
        "effectiveDateTime": "2022-07-05",
        "code": {
          "coding": [
            {
              "code": "2160-0",
              "display": "Creatinine"
            }
          ]
        },
        "valueQuantity": {
          "value": 1.72,
          "unit": "mg/dL"
        },
        "encounter": {
          "reference": "Encounter/enc-patient-6951-4"
        }
      }
    },
    {
      "resource": {
        "resourceType": "Encounter",
        "id": "enc-patient-6951-5",
        "status": "finished",
        "period": {
          "start": "2022-07-30"
        }
      }
    },
    {
      "resource": {
        "resourceType": "Observation",
        "effectiveDateTime": "2022-07-30",
        "code": {
          "coding": [
            {
              "code": "2160-0",
              "display": "Creatinine"
            }
          ]
        },
        "valueQuantity": {
          "value": 1.5,
          "unit": "mg/dL"
        },
        "encounter": {
          "reference": "Encounter/enc-patient-6951-5"
        }
      }
    }
  ]
}