{
  "resourceType": "Bundle",
  "id": "e886b0ca-fcb3-45b2-b9e8-db7a52bc77a9",
  "type": "collection",
  "entry": [
    {
      "resource": {
        "resourceType": "Patient",
        "id": "patient-0636",
        "gender": "female",
        "birthDate": "1982-01-17",
        "meta": {
          "lastUpdated": "2026-01-06"
        },
        "extension": [
          {
            "valueBoolean": true
          }
        ],
        "_recordStart": "2020-08-18"
      }
    },
    {
      "resource": {
        "resourceType": "Condition",
        "clinicalStatus": {
          "coding": [
            {
              "code": "active"
            }
          ]
        },
        "severity": {
          "text": "moderate"
        },
        "code": {
          "coding": [
            {
              "code": "D64.9",
              "display": "Anemia"
            }
          ]
        }
      }
    },
    {
      "resource": {
        "resourceType": "Condition",
        "clinicalStatus": {
          "coding": [
            {
              "code": "active"
            }
          ]
        },
        "severity": {
          "text": "severe"
        },
        "code": {
          "coding": [
            {
              "code": "J44.9",
              "display": "COPD"
            }
          ]
        }
      }
    },
    {
      "resource": {
        "resourceType": "Condition",
        "clinicalStatus": {
          "coding": [
            {
              "code": "active"
            }
          ]
        },
        "severity": {
          "text": "mild"
        },
        "code": {
          "coding": [
            {
              "code": "E11.9",
              "display": "Type 2 Diabetes Mellitus"
            }
          ]
        }
      }
    },
    {
      "resource": {
        "resourceType": "Condition",
        "clinicalStatus": {
          "coding": [
            {
              "code": "active"
            }
          ]
        },
        "severity": {
          "text": "severe"
        },
        "code": {
          "coding": [
            {
              "code": "I25.10",
              "display": "Coronary Artery Disease"
            }
          ]
        }
      }
    },
    {
      "resource": {
        "resourceType": "Encounter",
        "id": "enc-patient-0636-0",
        "status": "finished",
        "period": {
          "start": "2021-01-02"
        }
      }
    },
    {
      "resource": {
        "resourceType": "Observation",
        "effectiveDateTime": "2021-01-02",
        "code": {
          "coding": [
            {
              "code": "4548-4",
              "display": "Hemoglobin A1c"
            }
          ]
        },
        "valueQuantity": {
          "value": 9.09,
          "unit": "%"
        },
        "encounter": {
          "reference": "Encounter/enc-patient-0636-0"
        }
      }
    },
    {
      "resource": {
        "resourceType": "Encounter",
        "id": "enc-patient-0636-1",
        "status": "finished",
        "period": {
          "start": "2021-08-28"
        }
      }
    },
    {
      "resource": {
        "resourceType": "Observation",
        "effectiveDateTime": "2021-08-28",
        "code": {
          "coding": [
            {
              "code": "4548-4",
              "display": "Hemoglobin A1c"
            }
          ]
        },
        "valueQuantity": {
          "value": 8.48,
          "unit": "%"
        },
        "encounter": {
          "reference": "Encounter/enc-patient-0636-1"
        }
      }
    },
    {
      "resource": {
        "resourceType": "Encounter",
        "id": "enc-patient-0636-2",
        "status": "finished",
        "period": {
          "start": "2021-12-19"
        }
      }
    },
    {
      "resource": {
        "resourceType": "Observation",
        "effectiveDateTime": "2021-12-19",
        "code": {
          "coding": [
            {
              "code": "4548-4",
              "display": "Hemoglobin A1c"
            }
          ]
        },
        "valueQuantity": {
          "value": 6.96,
          "unit": "%"
        },
        "encounter": {
          "reference": "Encounter/enc-patient-0636-2"
        }
      }
    },
    {
      "resource": {
        "resourceType": "Encounter",
        "id": "enc-patient-0636-3",
        "status": "finished",
        "period": {
          "start": "2022-01-21"
        }
      }
    },
    {
      "resource": {
        "resourceType": "Observation",
        "effectiveDateTime": "2022-01-21",
        "code": {
          "coding": [
            {
              "code": "4548-4",
              "display": "Hemoglobin A1c"
            }
          ]
        },
        "valueQuantity": {
          "value": 9.52,
          "unit": "%"
        },
        "encounter": {
          "reference": "Encounter/enc-patient-0636-3"
        }
      }
    },
    {
      "resource": {
        "resourceType": "Encounter",
        "id": "enc-patient-0636-4",
        "status": "finished",
        "period": {
          "start": "2022-08-12"
        }
      }
    },
    {
      "resource": {
        "resourceType": "Observation",
        "effectiveDateTime": "2022-08-12",
        "code": {
          "coding": [
            {
              "code": "4548-4",
              "display": "Hemoglobin A1c"
            }
          ]
        },
        "valueQuantity": {
          "value": 9.12,
          "unit": "%"
        },
        "encounter": {
          "reference": "Encounter/enc-patient-0636-4"
        }
      }
    }
  ]
}