{
  "resourceType": "Bundle",
  "id": "7d6ac288-aeb0-438a-9e45-4f03599cd067",
  "type": "collection",
  "entry": [
    {
      "resource": {
        "resourceType": "Patient",
        "id": "patient-4202",
        "gender": "male",
        "birthDate": "1964-01-22",
        "meta": {
          "lastUpdated": "2026-01-06"
        },
        "extension": [
          {
            "valueBoolean": true
          }
        ],
        "_recordStart": "2020-03-24"
      }
    },
    {
      "resource": {
        "resourceType": "Condition",
        "clinicalStatus": {
          "coding": [
            {
              "code": "active"
            }
          ]
        },
        "severity": {
          "text": "mild"
        },
        "code": {
          "coding": [
            {
              "code": "E78.5",
              "display": "Hyperlipidemia"
            }
          ]
        }
      }
    },
    {
      "resource": {
        "resourceType": "Condition",
        "clinicalStatus": {
          "coding": [
            {
              "code": "active"
            }
          ]
        },
        "severity": {
          "text": "mild"
        },
        "code": {
          "coding": [
            {
              "code": "F32.9",
              "display": "Depression"
            }
          ]
        }
      }
    },
    {
      "resource": {
        "resourceType": "Condition",
        "clinicalStatus": {
          "coding": [
            {
              "code": "active"
            }
          ]
        },
        "severity": {
          "text": "mild"
        },
        "code": {
          "coding": [
            {
              "code": "E11.9",
              "display": "Type 2 Diabetes Mellitus"
            }
          ]
        }
      }
    },
    {
      "resource": {
        "resourceType": "Condition",
        "clinicalStatus": {
          "coding": [
            {
              "code": "active"
            }
          ]
        },
        "severity": {
          "text": "mild"
        },
        "code": {
          "coding": [
            {
              "code": "E66.9",
              "display": "Obesity"
            }
          ]
        }
      }
    },
    {
      "resource": {
        "resourceType": "Encounter",
        "id": "enc-patient-4202-0",
        "status": "finished",
        "period": {
          "start": "2020-07-17"
        }
      }
    },
    {
      "resource": {
        "resourceType": "Observation",
        "effectiveDateTime": "2020-07-17",
        "code": {
          "coding": [
            {
              "code": "2093-3",
              "display": "Total Cholesterol"
            }
          ]
        },
        "valueQuantity": {
          "value": 252.43,
          "unit": "mg/dL"
        },
        "encounter": {
          "reference": "Encounter/enc-patient-4202-0"
        }
      }
    },
    {
      "resource": {
        "resourceType": "Observation",
        "effectiveDateTime": "2020-07-17",
        "code": {
          "coding": [
            {
              "code": "4548-4",
              "display": "Hemoglobin A1c"
            }
          ]
        },
        "valueQuantity": {
          "value": 10.06,
          "unit": "%"
        },
        "encounter": {
          "reference": "Encounter/enc-patient-4202-0"
        }
      }
    },
    {
      "resource": {
        "resourceType": "Encounter",
        "id": "enc-patient-4202-1",
        "status": "finished",
        "period": {
          "start": "2020-11-11"
        }
      }
    },
    {
      "resource": {
        "resourceType": "Observation",
        "effectiveDateTime": "2020-11-11",
        "code": {
          "coding": [
            {
              "code": "2093-3",
              "display": "Total Cholesterol"
            }
          ]
        },
        "valueQuantity": {
          "value": 283.57,
          "unit": "mg/dL"
        },
        "encounter": {
          "reference": "Encounter/enc-patient-4202-1"
        }
      }
    },
    {
      "resource": {
        "resourceType": "Observation",
        "effectiveDateTime": "2020-11-11",
        "code": {
          "coding": [
            {
              "code": "4548-4",
              "display": "Hemoglobin A1c"
            }
          ]
        },
        "valueQuantity": {
          "value": 10.64,
          "unit": "%"
        },
        "encounter": {
          "reference": "Encounter/enc-patient-4202-1"
        }
      }
    },
    {
      "resource": {
        "resourceType": "Encounter",
        "id": "enc-patient-4202-2",
        "status": "finished",
        "period": {
          "start": "2021-01-31"
        }
      }
    },
    {
      "resource": {
        "resourceType": "Observation",
        "effectiveDateTime": "2021-01-31",
        "code": {
          "coding": [
            {
              "code": "2093-3",
              "display": "Total Cholesterol"
            }
          ]
        },
        "valueQuantity": {
          "value": 277.52,
          "unit": "mg/dL"
        },
        "encounter": {
          "reference": "Encounter/enc-patient-4202-2"
        }
      }
    },
    {
      "resource": {
        "resourceType": "Observation",
        "effectiveDateTime": "2021-01-31",
        "code": {
          "coding": [
            {
              "code": "4548-4",
              "display": "Hemoglobin A1c"
            }
          ]
        },
        "valueQuantity": {
          "value": 8.43,
          "unit": "%"
        },
        "encounter": {
          "reference": "Encounter/enc-patient-4202-2"
        }
      }
    },
    {
      "resource": {
        "resourceType": "Encounter",
        "id": "enc-patient-4202-3",
        "status": "finished",
        "period": {
          "start": "2021-05-08"
        }
      }
    },
    {
      "resource": {
        "resourceType": "Observation",
        "effectiveDateTime": "2021-05-08",
        "code": {
          "coding": [
            {
              "code": "2093-3",
              "display": "Total Cholesterol"
            }
          ]
        },
        "valueQuantity": {
          "value": 228.49,
          "unit": "mg/dL"
        },
        "encounter": {
          "reference": "Encounter/enc-patient-4202-3"
        }
      }
    },
    {
      "resource": {
        "resourceType": "Observation",
        "effectiveDateTime": "2021-05-08",
        "code": {
          "coding": [
            {
              "code": "4548-4",
              "display": "Hemoglobin A1c"
            }
          ]
        },
        "valueQuantity": {
          "value": 10.67,
          "unit": "%"
        },
        "encounter": {
          "reference": "Encounter/enc-patient-4202-3"
        }
      }
    },
    {
      "resource": {
        "resourceType": "Encounter",
        "id": "enc-patient-4202-4",
        "status": "finished",
        "period": {
          "start": "2021-09-10"
        }
      }
    },
    {
      "resource": {
        "resourceType": "Observation",
        "effectiveDateTime": "2021-09-10",
        "code": {
          "coding": [
            {
              "code": "2093-3",
              "display": "Total Cholesterol"
            }
          ]
        },
        "valueQuantity": {
          "value": 168.6,
          "unit": "mg/dL"
        },
        "encounter": {
          "reference": "Encounter/enc-patient-4202-4"
        }
      }
    },
    {
      "resource": {
        "resourceType": "Observation",
        "effectiveDateTime": "2021-09-10",
        "code": {
          "coding": [
            {
              "code": "4548-4",
              "display": "Hemoglobin A1c"
            }
          ]
        },
        "valueQuantity": {
          "value": 10.91,
          "unit": "%"
        },
        "encounter": {
          "reference": "Encounter/enc-patient-4202-4"
        }
      }
    },
    {
      "resource": {
        "resourceType": "Encounter",
        "id": "enc-patient-4202-5",
        "status": "finished",
        "period": {
          "start": "2021-09-10"
        }
      }
    },
    {
      "resource": {
        "resourceType": "Observation",
        "effectiveDateTime": "2021-09-10",
        "code": {
          "coding": [
            {
              "code": "2093-3",
              "display": "Total Cholesterol"
            }
          ]
        },
        "valueQuantity": {
          "value": 176.73,
          "unit": "mg/dL"
        },
        "encounter": {
          "reference": "Encounter/enc-patient-4202-5"
        }
      }
    },
    {
      "resource": {
        "resourceType": "Observation",
        "effectiveDateTime": "2021-09-10",
        "code": {
          "coding": [
            {
              "code": "4548-4",
              "display": "Hemoglobin A1c"
            }
          ]
        },
        "valueQuantity": {
          "value": 10.41,
          "unit": "%"
        },
        "encounter": {
          "reference": "Encounter/enc-patient-4202-5"
        }
      }
    },
    {
      "resource": {
        "resourceType": "Encounter",
        "id": "enc-patient-4202-6",
        "status": "finished",
        "period": {
          "start": "2021-12-01"
        }
      }
    },
    {
      "resource": {
        "resourceType": "Observation",
        "effectiveDateTime": "2021-12-01",
        "code": {
          "coding": [
            {
              "code": "2093-3",
              "display": "Total Cholesterol"
            }
          ]
        },
        "valueQuantity": {
          "value": 228.47,
          "unit": "mg/dL"
        },
        "encounter": {
          "reference": "Encounter/enc-patient-4202-6"
        }
      }
    },
    {
      "resource": {
        "resourceType": "Observation",
        "effectiveDateTime": "2021-12-01",
        "code": {
          "coding": [
            {
              "code": "4548-4",
              "display": "Hemoglobin A1c"
            }
          ]
        },
        "valueQuantity": {
          "value": 8.71,
          "unit": "%"
        },
        "encounter": {
          "reference": "Encounter/enc-patient-4202-6"
        }
      }
    },
    {
      "resource": {
        "resourceType": "Encounter",
        "id": "enc-patient-4202-7",
        "status": "finished",
        "period": {
          "start": "2022-06-22"
        }
      }
    },
    {
      "resource": {
        "resourceType": "Observation",
        "effectiveDateTime": "2022-06-22",
        "code": {
          "coding": [
            {
              "code": "4548-4",
              "display": "Hemoglobin A1c"
            }
          ]
        },
        "valueQuantity": {
          "value": 8.34,
          "unit": "%"
        },
        "encounter": {
          "reference": "Encounter/enc-patient-4202-7"
        }
      }
    }
  ]
}