{
  "resourceType": "Bundle",
  "id": "68fae0df-25e4-4009-8697-71ce07d3bfcb",
  "type": "collection",
  "entry": [
    {
      "resource": {
        "resourceType": "Patient",
        "id": "patient-2380",
        "gender": "female",
        "birthDate": "1951-01-25",
        "meta": {
          "lastUpdated": "2027-04-07"
        },
        "extension": [
          {
            "valueBoolean": false
          }
        ],
        "_recordStart": "2024-02-17"
      }
    },
    {
      "resource": {
        "resourceType": "Condition",
        "clinicalStatus": {
          "coding": [
            {
              "code": "resolved"
            }
          ]
        },
        "severity": {
          "text": "severe"
        },
        "code": {
          "coding": [
            {
              "code": "J45.909",
              "display": "Asthma"
            }
          ]
        }
      }
    },
    {
      "resource": {
        "resourceType": "Condition",
        "clinicalStatus": {
          "coding": [
            {
              "code": "resolved"
            }
          ]
        },
        "severity": {
          "text": "severe"
        },
        "code": {
          "coding": [
            {
              "code": "D64.9",
              "display": "Anemia"
            }
          ]
        }
      }
    },
    {
      "resource": {
        "resourceType": "Encounter",
        "id": "enc-patient-2380-0",
        "status": "finished",
        "period": {
          "start": "2025-03-06"
        }
      }
    },
    {
      "resource": {
        "resourceType": "Encounter",
        "id": "enc-patient-2380-1",
        "status": "finished",
        "period": {
          "start": "2026-02-14"
        }
      }
    },
    {
      "resource": {
        "resourceType": "Encounter",
        "id": "enc-patient-2380-2",
        "status": "finished",
        "period": {
          "start": "2026-06-17"
        }
      }
    },
    {
      "resource": {
        "resourceType": "Encounter",
        "id": "enc-patient-2380-3",
        "status": "finished",
        "period": {
          "start": "2026-07-31"
        }
      }
    }
  ]
}